<?xml version="1.0" encoding="UTF-8"?>
<SliderGroups>
    <Group name="Fashions of the Huntsmen - HIMBO">
        <Member name="Fashions Of The Huntsmen- Bretonic Leather Armor (HIMBO-Trimmed)"/>
        <Member name="Fashions Of The Huntsmen- Bretonic Leather Armor HIMBO"/>
        <Member name="Fashions Of The Huntsmen- Bretonic Leather Boots (HIMBO)"/>
        <Member name="Fashions Of The Huntsmen- Bretonic Leather Bracers (HIMBO)"/>
        <Member name="Fashions Of The Huntsmen- Colonial Militia Armor (HIMBO)"/>
        <Member name="Fashions Of The Huntsmen- Colonial Militia Boots (HIMBO)"/>
        <Member name="Fashions Of the Huntsmen- Colonial Militia Gloves (HIMBO)"/>
        <Member name="Fashions Of The Huntsmen- Cyrodillic Studded Armor (Blue) HIMBO"/>
        <Member name="Fashions Of The Huntsmen- Cyrodillic Studded Armor (Brown) HIMBO"/>
        <Member name="Fashions Of The Huntsmen- Cyrodillic Studded Armor (Red) HIMBO"/>
        <Member name="Fashions Of The Huntsmen- Cyrodillic Studded Armor Gauntlets HIMBO"/>
        <Member name="Fashions Of The Huntsmen- Elven Leather Boots HIMBO"/>
        <Member name="Fashions of The Huntsmen- Elven Leather Cuirass ALT for HIMBO"/>
        <Member name="Fashions of The Huntsmen- Elven Leather Cuirass for HIMBO"/>
        <Member name="Fashions of the Huntsmen- Fletcher&apos;s Leather Armor for HIMBO"/>
        <Member name="Fashions of the Huntsmen- Fletcher&apos;s Leather Boots for HIMBO"/>
        <Member name="Fashions of the Huntsmen- Fletcher&apos;s Leather Gauntlets for HIMBO"/>
        <Member name="Fashions Of The Huntsmen- Human Skin Boots HIMBO"/>
        <Member name="Fashions Of The Huntsmen- Human Skin Cuirass (Trimmed) HIMBO"/>
        <Member name="Fashions Of The Huntsmen- Human Skin Cuirass HIMBO"/>
        <Member name="Fashions Of the Huntsmen- Khajiiti Leather Armor (Trimmed) HIMBO"/>
        <Member name="Fashions Of the Huntsmen- Khajiiti Leather Armor Boots HIMBO"/>
        <Member name="Fashions Of the Huntsmen- Khajiiti Leather Armor HIMBO"/>
        <Member name="Fashions Of the Huntsmen- Khajiiti Leather Gauntlets HIMBO"/>
        <Member name="Fashions Of the Huntsmen- Khajiiti Leather Gauntlets HIMBO (Beast)"/>
        <Member name="Fashions Of the Huntsmen- Orcish Leather Armor (Trimmed) HIMBO"/>
        <Member name="Fashions Of the Huntsmen- Orcish Leather Armor Boots HIMBO"/>
        <Member name="Fashions Of the Huntsmen- Orcish Leather Armor Helmet (Argonian) HIMBO"/>
        <Member name="Fashions Of the Huntsmen- Orcish Leather Armor Helmet (Khajiit) HIMBO"/>
        <Member name="Fashions Of the Huntsmen- Orcish Leather Armor Helmet HIMBO"/>
        <Member name="Fashions Of the Huntsmen- Orcish Leather Armor HIMBO"/>
        <Member name="Fashions Of the Huntsmen- Orcish Leather Gauntlets HIMBO"/>
        <Member name="Fashions Of The Huntsmen- Valenwood Leather Armor (Trimmed) HIMBO"/>
        <Member name="Fashions Of The Huntsmen- Valenwood Leather Armor HIMBO"/>
        <Member name="Fashions Of The Huntsmen- Valenwood Leather Boots HIMBO"/>
        <Member name="Fashions Of The Huntsmen- Valenwood Leather Gauntlets HIMBO"/>
        <Member name="Fashions Of The Huntsmen- Valenwood Leather Helmet (Argonian) HIMBO"/>
        <Member name="Fashions Of The Huntsmen- Valenwood Leather Helmet (Khajiit) HIMBO"/>
        <Member name="Fashions Of The Huntsmen- Valenwood Leather Helmet HIMBO"/>
        <Member name="Fashions Of the Huntsmen-Atmoran Leather Armor HIMBO"/>
        <Member name="Fashions Of the Huntsmen-Atmoran Leather Boots HIMBO"/>
        <Member name="Fashions Of the Huntsmen-Atmoran Leather Gauntlets HIMBO"/>
        <Member name="Fashions Of The Huntsmen-Cyrodillic Studded Boots HIMBO"/>
    </Group>
    <Group name="HIMBO">
        <Member name="Fashions Of The Huntsmen- Bretonic Leather Armor (HIMBO-Trimmed)"/>
        <Member name="Fashions Of The Huntsmen- Bretonic Leather Armor HIMBO"/>
        <Member name="Fashions Of The Huntsmen- Bretonic Leather Boots (HIMBO)"/>
        <Member name="Fashions Of The Huntsmen- Bretonic Leather Bracers (HIMBO)"/>
        <Member name="Fashions Of The Huntsmen- Colonial Militia Armor (HIMBO)"/>
        <Member name="Fashions Of The Huntsmen- Colonial Militia Boots (HIMBO)"/>
        <Member name="Fashions Of the Huntsmen- Colonial Militia Gloves (HIMBO)"/>
        <Member name="Fashions Of The Huntsmen- Cyrodillic Studded Armor (Blue) HIMBO"/>
        <Member name="Fashions Of The Huntsmen- Cyrodillic Studded Armor (Brown) HIMBO"/>
        <Member name="Fashions Of The Huntsmen- Cyrodillic Studded Armor (Red) HIMBO"/>
        <Member name="Fashions Of The Huntsmen- Cyrodillic Studded Armor Gauntlets HIMBO"/>
        <Member name="Fashions Of The Huntsmen- Elven Leather Boots HIMBO"/>
        <Member name="Fashions of The Huntsmen- Elven Leather Cuirass ALT for HIMBO"/>
        <Member name="Fashions of The Huntsmen- Elven Leather Cuirass for HIMBO"/>
        <Member name="Fashions of the Huntsmen- Fletcher&apos;s Leather Armor for HIMBO"/>
        <Member name="Fashions of the Huntsmen- Fletcher&apos;s Leather Boots for HIMBO"/>
        <Member name="Fashions of the Huntsmen- Fletcher&apos;s Leather Gauntlets for HIMBO"/>
        <Member name="Fashions Of The Huntsmen- Human Skin Boots HIMBO"/>
        <Member name="Fashions Of The Huntsmen- Human Skin Cuirass (Trimmed) HIMBO"/>
        <Member name="Fashions Of The Huntsmen- Human Skin Cuirass HIMBO"/>
        <Member name="Fashions Of the Huntsmen- Khajiiti Leather Armor (Trimmed) HIMBO"/>
        <Member name="Fashions Of the Huntsmen- Khajiiti Leather Armor Boots HIMBO"/>
        <Member name="Fashions Of the Huntsmen- Khajiiti Leather Armor HIMBO"/>
        <Member name="Fashions Of the Huntsmen- Khajiiti Leather Gauntlets HIMBO"/>
        <Member name="Fashions Of the Huntsmen- Khajiiti Leather Gauntlets HIMBO (Beast)"/>
        <Member name="Fashions Of the Huntsmen- Orcish Leather Armor (Trimmed) HIMBO"/>
        <Member name="Fashions Of the Huntsmen- Orcish Leather Armor Boots HIMBO"/>
        <Member name="Fashions Of the Huntsmen- Orcish Leather Armor Helmet (Argonian) HIMBO"/>
        <Member name="Fashions Of the Huntsmen- Orcish Leather Armor Helmet (Khajiit) HIMBO"/>
        <Member name="Fashions Of the Huntsmen- Orcish Leather Armor Helmet HIMBO"/>
        <Member name="Fashions Of the Huntsmen- Orcish Leather Armor HIMBO"/>
        <Member name="Fashions Of the Huntsmen- Orcish Leather Gauntlets HIMBO"/>
        <Member name="Fashions Of The Huntsmen- Valenwood Leather Armor (Trimmed) HIMBO"/>
        <Member name="Fashions Of The Huntsmen- Valenwood Leather Armor HIMBO"/>
        <Member name="Fashions Of The Huntsmen- Valenwood Leather Boots HIMBO"/>
        <Member name="Fashions Of The Huntsmen- Valenwood Leather Gauntlets HIMBO"/>
        <Member name="Fashions Of The Huntsmen- Valenwood Leather Helmet (Argonian) HIMBO"/>
        <Member name="Fashions Of The Huntsmen- Valenwood Leather Helmet (Khajiit) HIMBO"/>
        <Member name="Fashions Of The Huntsmen- Valenwood Leather Helmet HIMBO"/>
        <Member name="Fashions Of the Huntsmen-Atmoran Leather Armor HIMBO"/>
        <Member name="Fashions Of the Huntsmen-Atmoran Leather Boots HIMBO"/>
        <Member name="Fashions Of the Huntsmen-Atmoran Leather Gauntlets HIMBO"/>
        <Member name="Fashions Of The Huntsmen-Cyrodillic Studded Boots HIMBO"/>
    </Group>
</SliderGroups>
